floclib/__init__.py
floclib/asd.py
floclib/cli.py
floclib/cstr.py
floclib/fit.py
floclib/io.py
floclib/tests/floclib_main.py
floclib-0.1.3.dist-info/METADATA
floclib-0.1.3.dist-info/WHEEL
floclib-0.1.3.dist-info/entry_points.txt
floclib-0.1.3.dist-info/top_level.txt
floclib-0.1.3.dist-info/RECORD
