Metadata-Version: 2.4
Name: floclib
Version: 0.1.3
Summary: Flocculation kinetic modelling and retention time simulation toolkit
Author-email: "Abayomi O. Bankole" <bankoleabayomi3@gmail.com>, Rodrigo Moruzzi <rodrigo.Moruzzi@unesp.br>, "Rogério G. Negri" <rogerio.negri@unesp.br>
Maintainer-email: "Abayomi O. Bankole" <bankoleabayomi3@gmail.com>
Requires-Python: >=3.11
Requires-Dist: numpy<2.0,>=1.24
Requires-Dist: pandas<2.2,>=2.1
Requires-Dist: scipy<2.0,>=1.10
Requires-Dist: scikit-image<0.24,>=0.23
Requires-Dist: opencv-python-headless<5.0,>=4.6
Requires-Dist: matplotlib<=3.8,>=3.7
Requires-Dist: pyswarms<1.4,>=1.3
Requires-Dist: boto3<1.40,>=1.37
Requires-Dist: psutil<6.0,>=5.9
Requires-Dist: gunicorn<23.1,>=23.0
Requires-Dist: flask<3.2,>=3.1
Requires-Dist: scikit-learn<=1.5,>=1.1
Requires-Dist: fastparquet<=2024.11,>=2023
